{
    "layout": "agenda.njk",
    "page": {
        "title": "ServerlessDays Cardiff - Agenda",
        "description": "One Day. One Track. One Community",
        "url": "https://cardiff.serverlessdays.io/agenda",
        "image": "https://res.cloudinary.com/serverlessdays/image/upload/v1560353326/London/2019/serverlessdays_card.jpg"
    },
    "agenda": [
    {
        "date": "13 Feburary 2020",
        "type": "date"
    },
    {
        "time": "08:30",
        "name": "Doors Open",
        "type": "break"
    },
    {
        "time": "09:15",
        "name": "Welcome Remarks",
        "speaker": [
            {
                "name": "ServerlessDays Team"
            }
        ],
        "type": "talk"
    },
    {
        "time": "09.30",
        "name": "Agenda coming soon",
        "type": "break"
    }
  ]
}
